builder/__init__.py
builder/config.py
builder/data_helper.py
builder/engine.py
builder/file_cache.py
builder/main.py
builder/models.py
builder/project.py
builder/schema.py
builder/schema_validator.py
builder/signing.py
builder/task_module.py
builder/utils.py
builder/version.txt
builder/java/__init__.py
builder/java/compile.py
builder/java/describe.py
builder/java/doc.py
builder/java/init.py
builder/java/java.py
builder/java/modules.py
builder/java/package.py
builder/java/pom.py
builder/java/resolver.py
builder/java/sync_ij.py
builder/java/test.py
builder/java/version_check.py
builder/java/xml_support.py
builder/jetbrains/__init__.py
builder/jetbrains/intellij.py
tests/__init__.py
tests/test_data_helper.py
tests/test_engine.py
tests/test_file_cache.py
tests/test_models.py
tests/test_project.py
tests/test_schema.py
tests/test_schema_validator.py
tests/test_signing.py
tests/test_support.py
tests/test_task_module.py
tests/test_utils.py
builder_tool-0.6.0.dist-info/LICENSE.md
builder_tool-0.6.0.dist-info/METADATA
builder_tool-0.6.0.dist-info/WHEEL
builder_tool-0.6.0.dist-info/entry_points.txt
builder_tool-0.6.0.dist-info/top_level.txt
builder_tool-0.6.0.dist-info/RECORD
