Metadata-Version: 2.1
Name: builder-tool
Version: 0.6.0
Summary: Software Builder Tool
Home-page: https://github.com/jskress/builder-tool
Author: Stephen Kress
Author-email: jskress@gmail.com
License: Apache 2.0
Project-URL: Documentation, https://builder-tool.readthedocs.io/
Project-URL: Code, https://github.com/jskress/builder-tool
Project-URL: Issue tracker, https://github.com/jskress/builder-tool/issues
Platform: UNKNOWN
Requires-Python: >=3.9.0
License-File: LICENSE.md
Requires-Dist: click
Requires-Dist: requests
Requires-Dist: PyYAML
Requires-Dist: stringcase
